work_yapi/__init__.py
work_yapi/base.py
work_yapi/cli.py
work_yapi/group.py
work_yapi/projec.py
work_yapi/user.py
work_yapi/work_yapi.py
work_yapi-0.1.0.dist-info/AUTHORS.rst
work_yapi-0.1.0.dist-info/LICENSE
work_yapi-0.1.0.dist-info/METADATA
work_yapi-0.1.0.dist-info/WHEEL
work_yapi-0.1.0.dist-info/entry_points.txt
work_yapi-0.1.0.dist-info/top_level.txt
work_yapi-0.1.0.dist-info/RECORD
