Metadata-Version: 2.1
Name: work-yapi
Version: 0.1.0
Summary: YApi python SDK
Home-page: https://github.com/w89306768/work_yapi
Author: zhy
Author-email: 531691961@qq.com
License: MIT license
Keywords: work_yapi
Platform: UNKNOWN
Classifier: Development Status :: 2 - Pre-Alpha
Classifier: Intended Audience :: Developers
Classifier: License :: OSI Approved :: MIT License
Classifier: Natural Language :: English
Classifier: Programming Language :: Python :: 3
Classifier: Programming Language :: Python :: 3.6
Classifier: Programming Language :: Python :: 3.7
Classifier: Programming Language :: Python :: 3.8
Requires-Python: >=3.6
Requires-Dist: Click (>=7.0)
Requires-Dist: requests
